Workbook
Name Slicer_Category: #N/A
Name Slicer_Order_Date: #N/A
Name Slicer_Region: #N/A
Name Slicer_Sales_Rep: #N/A

Sheet Sales_Data
A1: Order_ID | B1: Order_Date | C1: Region | D1: Sales_Rep | E1: Product_ID | F1: Quantity | G1: Unit_Price | H1: Product_Name | I1: Category | J1: Cost_Price | K1: Total_sales | L1: Total_Cost | M1: Profit | N1: Target_sales | O1: Achievement_%
A2: O0001 | B2: 2025-03-08 | C2: West | D2: Arjun | E2: P102 | F2: 5 | G2: 2034 | H2: =_xlfn.XLOOKUP(E2, Product_Master!A:A, Product_Master!B:B) -> Mobile | I2: =_xlfn.XLOOKUP(E2, Product_Master!A:A, Product_Master!C:C) -> Electronics | J2: =_xlfn.XLOOKUP(E2, Product_Master!A:A, Product_Master!D:D) -> 18000 | K2: =F2*G2 -> 10170 | L2: =F2*J2 -> 90000 | M2: =K2-L2 -> -79830 | N2: =_xlfn.XLOOKUP(D2, Sales_Rep_Master!A:A, Sales_Rep_Master!B:B) -> 920000 | O2: =K2/N2 -> 0.011054348
A3: O0002 | B3: 2025-12-08 | C3: West | D3: Vikas | E3: P104 | F3: 1 | G3: 2220 | H3: =_xlfn.XLOOKUP(E3, Product_Master!A:A, Product_Master!B:B) -> Chair | I3: =_xlfn.XLOOKUP(E3, Product_Master!A:A, Product_Master!C:C) -> Furniture | J3: =_xlfn.XLOOKUP(E3, Product_Master!A:A, Product_Master!D:D) -> 2500 | K3: =F3*G3 -> 2220 | L3: =F3*J3 -> 2500 | M3: =K3-L3 -> -280 | N3: =_xlfn.XLOOKUP(D3, Sales_Rep_Master!A:A, Sales_Rep_Master!B:B) -> 880000 | O3: =K3/N3 -> 0.0025227273
A4: O0003 | B4: 2025-02-20 | C4: South | D4: Priya | E4: P103 | F4: 13 | G4: 1172 | H4: =_xlfn.XLOOKUP(E4, Product_Master!A:A, Product_Master!B:B) -> Headphones | I4: =_xlfn.XLOOKUP(E4, Product_Master!A:A, Product_Master!C:C) -> Electronics | J4: =_xlfn.XLOOKUP(E4, Product_Master!A:A, Product_Master!D:D) -> 2000 | K4: =F4*G4 -> 15236 | L4: =F4*J4 -> 26000 | M4: =K4-L4 -> -10764 | N4: =_xlfn.XLOOKUP(D4, Sales_Rep_Master!A:A, Sales_Rep_Master!B:B) -> 950000 | O4: =K4/N4 -> 0.016037895
A5: O0004 | B5: 2025-02-07 | C5: South | D5: Priya | E5: P106 | F5: 5 | G5: 902 | H5: =_xlfn.XLOOKUP(E5, Product_Master!A:A, Product_Master!B:B) -> Sofa | I5: =_xlfn.XLOOKUP(E5, Product_Master!A:A, Product_Master!C:C) -> Furniture | J5: =_xlfn.XLOOKUP(E5, Product_Master!A:A, Product_Master!D:D) -> 15000 | K5: =F5*G5 -> 4510 | L5: =F5*J5 -> 75000 | M5: =K5-L5 -> -70490 | N5: =_xlfn.XLOOKUP(D5, Sales_Rep_Master!A:A, Sales_Rep_Master!B:B) -> 950000 | O5: =K5/N5 -> 0.0047473684
A6: O0005 | B6: 2025-12-04 | C6: East | D6: Sneha | E6: P101 | F6: 9 | G6: 4018 | H6: =_xlfn.XLOOKUP(E6, Product_Master!A:A, Product_Master!B:B) -> Laptop | I6: =_xlfn.XLOOKUP(E6, Product_Master!A:A, Product_Master!C:C) -> Electronics | J6: =_xlfn.XLOOKUP(E6, Product_Master!A:A, Product_Master!D:D) -> 35000 | K6: =F6*G6 -> 36162 | L6: =F6*J6 -> 315000 | M6: =K6-L6 -> -278838 | N6: =_xlfn.XLOOKUP(D6, Sales_Rep_Master!A:A, Sales_Rep_Master!B:B) -> 800000 | O6: =K6/N6 -> 0.0452025
A7: O0006 | B7: 2025-10-25 | C7: West | D7: Vikas | E7: P104 | F7: 5 | G7: 6915 | H7: =_xlfn.XLOOKUP(E7, Product_Master!A:A, Product_Master!B:B) -> Chair | I7: =_xlfn.XLOOKUP(E7, Product_Master!A:A, Product_Master!C:C) -> Furniture | J7: =_xlfn.XLOOKUP(E7, Product_Master!A:A, Product_Master!D:D) -> 2500 | K7: =F7*G7 -> 34575 | L7: =F7*J7 -> 12500 | M7: =K7-L7 -> 22075 | N7: =_xlfn.XLOOKUP(D7, Sales_Rep_Master!A:A, Sales_Rep_Master!B:B) -> 880000 | O7: =K7/N7 -> 0.039289773
A8: O0007 | B8: 2025-06-03 | C8: North | D8: Vikas | E8: P107 | F8: 1 | G8: 1591 | H8: =_xlfn.XLOOKUP(E8, Product_Master!A:A, Product_Master!B:B) -> Jacket | I8: =_xlfn.XLOOKUP(E8, Product_Master!A:A, Product_Master!C:C) -> Clothing | J8: =_xlfn.XLOOKUP(E8, Product_Master!A:A, Product_Master!D:D) -> 1500 | K8: =F8*G8 -> 1591 | L8: =F8*J8 -> 1500 | M8: =K8-L8 -> 91 | N8: =_xlfn.XLOOKUP(D8, Sales_Rep_Master!A:A, Sales_Rep_Master!B:B) -> 880000 | O8: =K8/N8 -> 0.0018079545
A9: O0008 | B9: 2025-01-02 | C9: West | D9: Rahul | E9: P102 | F9: 3 | G9: 2844 | H9: =_xlfn.XLOOKUP(E9, Product_Master!A:A, Product_Master!B:B) -> Mobile | I9: =_xlfn.XLOOKUP(E9, Product_Master!A:A, Product_Master!C:C) -> Electronics | J9: =_xlfn.XLOOKUP(E9, Product_Master!A:A, Product_Master!D:D) -> 18000 | K9: =F9*G9 -> 8532 | L9: =F9*J9 -> 54000 | M9: =K9-L9 -> -45468 | N9: =_xlfn.XLOOKUP(D9, Sales_Rep_Master!A:A, Sales_Rep_Master!B:B) -> 850000 | O9: =K9/N9 -> 0.010037647
A10: O0009 | B10: 2025-08-21 | C10: South | D10: Priya | E10: P105 | F10: 9 | G10: 6821 | H10: =_xlfn.XLOOKUP(E10, Product_Master!A:A, Product_Master!B:B) -> Table | I10: =_xlfn.XLOOKUP(E10, Product_Master!A:A, Product_Master!C:C) -> Furniture | J10: =_xlfn.XLOOKUP(E10, Product_Master!A:A, Product_Master!D:D) -> 7000 | K10: =F10*G10 -> 61389 | L10: =F10*J10 -> 63000 | M10: =K10-L10 -> -1611 | N10: =_xlfn.XLOOKUP(D10, Sales_Rep_Master!A:A, Sales_Rep_Master!B:B) -> 950000 | O10: =K10/N10 -> 0.06462
A11: O0010 | B11: 2025-12-12 | C11: East | D11: Vikas | E11: P101 | F11: 14 | G11: 603 | H11: =_xlfn.XLOOKUP(E11, Product_Master!A:A, Product_Master!B:B) -> Laptop | I11: =_xlfn.XLOOKUP(E11, Product_Master!A:A, Product_Master!C:C) -> Electronics | J11: =_xlfn.XLOOKUP(E11, Product_Master!A:A, Product_Master!D:D) -> 35000 | K11: =F11*G11 -> 8442 | L11: =F11*J11 -> 490000 | M11: =K11-L11 -> -481558 | N11: =_xlfn.XLOOKUP(D11, Sales_Rep_Master!A:A, Sales_Rep_Master!B:B) -> 880000 | O11: =K11/N11 -> 0.0095931818
A12: O0011 | B12: 2025-03-24 | C12: South | D12: Arjun | E12: P106 | F12: 2 | G12: 3879 | H12: =_xlfn.XLOOKUP(E12, Product_Master!A:A, Product_Master!B:B) -> Sofa | I12: =_xlfn.XLOOKUP(E12, Product_Master!A:A, Product_Master!C:C) -> Furniture | J12: =_xlfn.XLOOKUP(E12, Product_Master!A:A, Product_Master!D:D) -> 15000 | K12: =F12*G12 -> 7758 | L12: =F12*J12 -> 30000 | M12: =K12-L12 -> -22242 | N12: =_xlfn.XLOOKUP(D12, Sales_Rep_Master!A:A, Sales_Rep_Master!B:B) -> 920000 | O12: =K12/N12 -> 0.0084326087
A13: O0012 | B13: 2025-02-19 | C13: East | D13: Arjun | E13: P106 | F13: 1 | G13: 7391 | H13: =_xlfn.XLOOKUP(E13, Product_Master!A:A, Product_Master!B:B) -> Sofa | I13: =_xlfn.XLOOKUP(E13, Product_Master!A:A, Product_Master!C:C) -> Furniture | J13: =_xlfn.XLOOKUP(E13, Product_Master!A:A, Product_Master!D:D) -> 15000 | K13: =F13*G13 -> 7391 | L13: =F13*J13 -> 15000 | M13: =K13-L13 -> -7609 | N13: =_xlfn.XLOOKUP(D13, Sales_Rep_Master!A:A, Sales_Rep_Master!B:B) -> 920000 | O13: =K13/N13 -> 0.0080336957
... A651: O0650 | B651: 2025-09-11 | C651: West | D651: Arjun | E651: P102 | F651: 4 | G651: 2219 | H651: =_xlfn.XLOOKUP(E651, Product_Master!A:A, Product_Master!B:B) -> Mobile | I651: =_xlfn.XLOOKUP(E651, Product_Master!A:A, Product_Master!C:C) -> Electronics | J651: =_xlfn.XLOOKUP(E651, Product_Master!A:A, Product_Master!D:D) -> 18000 | K651: =F651*G651 -> 8876 | L651: =F651*J651 -> 72000 | M651: =K651-L651 -> -63124 | N651: =_xlfn.XLOOKUP(D651, Sales_Rep_Master!A:A, Sales_Rep_Master!B:B) -> 920000 | O651: =K651/N651 -> 0.0096478261

Sheet Product_Master
A1: Product_ID | B1: Product_Name | C1: Category | D1: Cost_Price
A2: P101 | B2: Laptop | C2: Electronics | D2: 35000
A3: P102 | B3: Mobile | C3: Electronics | D3: 18000
A4: P103 | B4: Headphones | C4: Electronics | D4: 2000
A5: P104 | B5: Chair | C5: Furniture | D5: 2500
A6: P105 | B6: Table | C6: Furniture | D6: 7000
A7: P106 | B7: Sofa | C7: Furniture | D7: 15000
A8: P107 | B8: Jacket | C8: Clothing | D8: 1500
A9: P108 | B9: Shoes | C9: Clothing | D9: 2000

Sheet Sales_Rep_Master
A1: Sales_Rep | B1: Target_Sales
A2: Amit | B2: 900000
A3: Rahul | B3: 850000
A4: Priya | B4: 950000
A5: Sneha | B5: 800000
A6: Vikas | B6: 880000
A7: Neha | B7: 870000
A8: Arjun | B8: 920000
A9: Karan | B9: 890000

Sheet Region Wise Sales & Profit
A2: Pivot_Region
A5: Row Labels | B5: Sum of Total_sales | C5: Sum of Profit
A6: East | B6: 5026376 | C6: -7814124
A7: North | B7: 4896499 | C7: -8391501
A8: South | B8: 5543129 | C8: -5394371
A9: West | B9: 5888294 | C9: -6969706
A10: Grand Total | B10: 21354298 | C10: -28569702

Sheet Category wise sales
A2: Pivot_Category
A5: Row Labels | B5: Sum of Total_sales
A6: Clothing | B6: 5877819
A7: Electronics | B7: 7954974
A8: Furniture | B8: 7521505
A9: Grand Total | B9: 21354298

Sheet Sales Rep Performance
A2: Pivot_SalesRep
A5: Row Labels | B5: Sum of Total_sales | C5: Sum of Profit
A6: Amit | B6: 2891462 | C6: -2620038
A7: Arjun | B7: 2961627 | C7: -2771373
A8: Karan | B8: 2414107 | C8: -3345893
A9: Neha | B9: 2803251 | C9: -3251749
A10: Priya | B10: 2622263 | C10: -4269237
A11: Rahul | B11: 2444343 | C11: -3474157
A12: Sneha | B12: 2536155 | C12: -4874845
A13: Vikas | B13: 2681090 | C13: -3962410
A14: Grand Total | B14: 21354298 | C14: -28569702

Sheet Monthly Trend
A2: Pivot_Monthly
A5: Row Labels | B5: Sum of Total_sales
A6: 2025-01-01 | B6: 139086
A7: 2025-01-02 | B7: 51886
A8: 2025-01-03 | B8: 71435
A9: 2025-01-04 | B9: 119240
A10: 2025-01-05 | B10: 58230
A11: 2025-01-06 | B11: 113786
A12: 2025-01-07 | B12: 5436
A13: 2025-01-08 | B13: 102594
A14: 2025-01-09 | B14: 124418
A15: 2025-01-10 | B15: 42259
A16: 2025-01-11 | B16: 21548
A17: 2025-01-12 | B17: 20488
... A304: Grand Total | B304: 21354298

Sheet KPIs
A3: Sum of Total_sales | B3: Sum of Quantity | C3: Sum of Target_sales | D3: Sum of Profit
A4: 21354298 | B4: 5162 | C4: 575040000 | D4: -28569702

Sheet Fliter

Sheet Dashboard
A1: Total Sales | F1: Total Profit | K1: Total Target | P1: Total Quantity
A6: =GETPIVOTDATA("Sum of Total_sales",KPIs!$A$3) -> 21354298 | F6: =GETPIVOTDATA("Sum of Profit",KPIs!$A$3) -> -28569702 | K6: =GETPIVOTDATA("Sum of Target_sales",KPIs!$A$3) -> 575040000 | P6: =GETPIVOTDATA("Sum of Quantity",KPIs!$A$3) -> 5162
